{"plantData":[{"thePlantRow":2,"thePlantColumn":4,"thePlantType":13,"growStage":2,"waterLevel":0,"love":28,"nextTime":1755331027,"needTool":1,"page":0},{"thePlantRow":0,"thePlantColumn":4,"thePlantType":6,"growStage":2,"waterLevel":0,"love":0,"nextTime":1755329264,"needTool":1,"page":0},{"thePlantRow":2,"thePlantColumn":6,"thePlantType":14,"growStage":2,"waterLevel":0,"love":33,"nextTime":1755330834,"needTool":1,"page":0},{"thePlantRow":0,"thePlantColumn":1,"thePlantType":0,"growStage":2,"waterLevel":0,"love":0,"nextTime":1755329694,"needTool":1,"page":0},{"thePlantRow":1,"thePlantColumn":7,"thePlantType":24,"growStage":2,"waterLevel":0,"love":0,"nextTime":1755329831,"needTool":1,"page":0},{"thePlantRow":1,"thePlantColumn":0,"thePlantType":25,"growStage":2,"waterLevel":0,"love":0,"nextTime":1755329215,"needTool":1,"page":0},{"thePlantRow":2,"thePlantColumn":3,"thePlantType":26,"growStage":2,"waterLevel":0,"love":0,"nextTime":1755329359,"needTool":1,"page":0},{"thePlantRow":1,"thePlantColumn":4,"thePlantType":23,"growStage":2,"waterLevel":0,"love":33,"nextTime":1755331810,"needTool":1,"page":0},{"thePlantRow":1,"thePlantColumn":6,"thePlantType":31,"growStage":2,"waterLevel":0,"love":0,"nextTime":1755329724,"needTool":1,"page":0},{"thePlantRow":0,"thePlantColumn":7,"thePlantType":20,"growStage":1,"waterLevel":0,"love":0,"nextTime":1755329484,"needTool":1,"page":0},{"thePlantRow":3,"thePlantColumn":6,"thePlantType":4,"growStage":2,"waterLevel":0,"love":0,"nextTime":1755330158,"needTool":1,"page":0},{"thePlantRow":1,"thePlantColumn":3,"thePlantType":30,"growStage":2,"waterLevel":0,"love":0,"nextTime":1755329579,"needTool":1,"page":0},{"thePlantRow":2,"thePlantColumn":7,"thePlantType":30,"growStage":1,"waterLevel":0,"love":0,"nextTime":1755329421,"needTool":1,"page":0},{"thePlantRow":1,"thePlantColumn":5,"thePlantType":11,"growStage":2,"waterLevel":0,"love":0,"nextTime":1755329392,"needTool":1,"page":0},{"thePlantRow":1,"thePlantColumn":1,"thePlantType":13,"growStage":2,"waterLevel":0,"love":0,"nextTime":1755329580,"needTool":1,"page":0},{"thePlantRow":0,"thePlantColumn":2,"thePlantType":10,"growStage":2,"waterLevel":0,"love":0,"nextTime":1755329879,"needTool":1,"page":0},{"thePlantRow":0,"thePlantColumn":5,"thePlantType":2,"growStage":2,"waterLevel":0,"love":0,"nextTime":1755329779,"needTool":1,"page":0},{"thePlantRow":3,"thePlantColumn":7,"thePlantType":3,"growStage":1,"waterLevel":100,"love":0,"nextTime":1755328634,"needTool":2,"page":0},{"thePlantRow":2,"thePlantColumn":2,"thePlantType":25,"growStage":2,"waterLevel":0,"love":0,"nextTime":1755329609,"needTool":1,"page":0},{"thePlantRow":0,"thePlantColumn":0,"thePlantType":6,"growStage":2,"waterLevel":0,"love":0,"nextTime":1755329544,"needTool":1,"page":0},{"thePlantRow":0,"thePlantColumn":3,"thePlantType":242,"growStage":1,"waterLevel":0,"love":0,"nextTime":1755329516,"needTool":1,"page":0},{"thePlantRow":1,"thePlantColumn":2,"thePlantType":1012,"growStage":0,"waterLevel":100,"love":0,"nextTime":1755328628,"needTool":2,"page":0},{"thePlantRow":0,"thePlantColumn":6,"thePlantType":1030,"growStage":0,"waterLevel":76,"love":0,"nextTime":1755328621,"needTool":1,"page":0},{"thePlantRow":2,"thePlantColumn":1,"thePlantType":19,"growStage":0,"waterLevel":0,"love":0,"nextTime":0,"needTool":1,"page":0},{"thePlantRow":3,"thePlantColumn":3,"thePlantType":6,"growStage":0,"waterLevel":0,"love":0,"nextTime":0,"needTool":1,"page":0},{"thePlantRow":3,"thePlantColumn":5,"thePlantType":1,"growStage":0,"waterLevel":0,"love":0,"nextTime":0,"needTool":1,"page":0},{"thePlantRow":2,"thePlantColumn":5,"thePlantType":18,"growStage":0,"waterLevel":0,"love":0,"nextTime":0,"needTool":1,"page":0},{"thePlantRow":3,"thePlantColumn":2,"thePlantType":10,"growStage":0,"waterLevel":0,"love":0,"nextTime":0,"needTool":1,"page":0},{"thePlantRow":2,"thePlantColumn":0,"thePlantType":0,"growStage":0,"waterLevel":0,"love":0,"nextTime":0,"needTool":1,"page":0},{"thePlantRow":3,"thePlantColumn":4,"thePlantType":12,"growStage":0,"waterLevel":0,"love":0,"nextTime":0,"needTool":1,"page":0},{"thePlantRow":3,"thePlantColumn":1,"thePlantType":3,"growStage":0,"waterLevel":0,"love":0,"nextTime":0,"needTool":1,"page":0},{"thePlantRow":3,"thePlantColumn":0,"thePlantType":23,"growStage":0,"waterLevel":0,"love":0,"nextTime":0,"needTool":1,"page":0}]}